flask_validation_extended/__init__.py
flask_validation_extended/exceptions.py
flask_validation_extended/params.py
flask_validation_extended/rules.py
flask_validation_extended/types.py
flask_validation_extended/utils.py
flask_validation_extended/vaildator.py
flask_validation_extended-0.2.1.dist-info/LICENSE
flask_validation_extended-0.2.1.dist-info/METADATA
flask_validation_extended-0.2.1.dist-info/WHEEL
flask_validation_extended-0.2.1.dist-info/top_level.txt
flask_validation_extended-0.2.1.dist-info/RECORD
