Metadata-Version: 2.1
Name: flask-validation-extended
Version: 0.2.1
Summary: Get and validate all Flask input parameters with easily!
Home-page: https://github.com/iml1111/flask-validation-extended
Author: IML
Author-email: shin10256@gmail.com
License: MIT
Keywords: flask validation extended
Platform: any
Classifier: Environment :: Web Environment
Classifier: Framework :: Flask
Classifier: Intended Audience :: Developers
Classifier: License :: OSI Approved :: MIT License
Classifier: Operating System :: OS Independent
Classifier: Programming Language :: Python :: 3.6
Classifier: Programming Language :: Python :: 3.7
Classifier: Programming Language :: Python :: 3.8
Classifier: Programming Language :: Python :: 3.9
Classifier: Topic :: Internet :: WWW/HTTP :: Dynamic Content
Classifier: Topic :: Software Development :: Libraries :: Python Modules
License-File: LICENSE
Requires-Dist: flask
